arteria/__init__.py
arteria/configuration.py
arteria/decorators.py
arteria/exceptions.py
arteria/testhelpers.py
arteria/web/__init__.py
arteria/web/app.py
arteria/web/handlers.py
arteria/web/routes.py
arteria/web/state.py
arteria-1.1.4.dist-info/LICENSE
arteria-1.1.4.dist-info/METADATA
arteria-1.1.4.dist-info/WHEEL
arteria-1.1.4.dist-info/top_level.txt
arteria-1.1.4.dist-info/RECORD
