Metadata-Version: 2.1
Name: arteria
Version: 1.1.4
Summary: Helper classes for the arteria project
Author: SNP&SEQ Technology Platform, Uppsala University
Keywords: bioinformatics
License-File: LICENSE
Requires-Dist: tornado (>=4.2.1)
Requires-Dist: PyYAML (>=3.13)
Requires-Dist: requests (>=2.20.0)
